promptstack/__init__.py
promptstack/exceptions.py
promptstack/openai_backend.py
promptstack/promptstack.py
promptstack/subprompt.py
promptstack-0.0.2.dist-info/LICENSE
promptstack-0.0.2.dist-info/METADATA
promptstack-0.0.2.dist-info/WHEEL
promptstack-0.0.2.dist-info/top_level.txt
promptstack-0.0.2.dist-info/RECORD
