Metadata-Version: 2.1
Name: promptstack
Version: 0.0.2
Summary: Promptstack is an LLM pompt/task management toolkit
Author-email: Bill Kish <bk@jiggy.ai>
Project-URL: Homepage, https://github.com/jiggy-ai/promptstack
Project-URL: Bug Tracker, https://github.com/jiggy-ai/promptstack/issues
Classifier: Programming Language :: Python :: 3
Classifier: License :: OSI Approved :: Apache Software License
Classifier: Operating System :: OS Independent
Requires-Python: >=3.7
License-File: LICENSE
Requires-Dist: pydantic
Requires-Dist: openai
Requires-Dist: transformers
Requires-Dist: loguru
